{"Id":"00edd992-7271-46ce-90a3-c148d87da32d","Words":[{"Id":1,"X":4,"Y":0,"Clue":3,"Question":"Перемывание косточек произведению искусства.","Answer":"КРИТИКА","Axis":"X"},{"Id":2,"X":0,"Y":1,"Clue":8,"Question":"Именно над ним чах Кощей в стихотворении Пушкина.","Answer":"ЗЛАТО","Axis":"X"},{"Id":3,"X":10,"Y":1,"Clue":9,"Question":"Приятная фантазия мечтателя.","Answer":"ГРЁЗА","Axis":"X"},{"Id":4,"X":4,"Y":2,"Clue":10,"Question":"Центральная часть колеса, маховика.","Answer":"СТУПИЦА","Axis":"X"},{"Id":5,"X":0,"Y":3,"Clue":13,"Question":"Старинный мешочек для хранения денег.","Answer":"МОШНА","Axis":"X"},{"Id":6,"X":10,"Y":3,"Clue":15,"Question":"И текстильный, и биологический материал.","Answer":"ТКАНЬ","Axis":"X"},{"Id":7,"X":5,"Y":4,"Clue":17,"Question":"Потомок европейских завоевателей в Латинской Америке.","Answer":"КРЕОЛ","Axis":"X"},{"Id":8,"X":0,"Y":5,"Clue":18,"Question":"Самая старинная порода норных собак.","Answer":"ТАКСА","Axis":"X"},{"Id":9,"X":10,"Y":5,"Clue":20,"Question":"В этом лондонском замке на службе состоят вороны.","Answer":"ТАУЭР","Axis":"X"},{"Id":10,"X":3,"Y":7,"Clue":22,"Question":"Современный способ изготовления книг.","Answer":"ПЕЧАТАНИЕ","Axis":"X"},{"Id":11,"X":0,"Y":8,"Clue":26,"Question":"Из неё шьют пододеяльники и простыни.","Answer":"БЯЗЬ","Axis":"X"},{"Id":12,"X":11,"Y":8,"Clue":28,"Question":"Горная порода, из которой можно добыть какой-нибудь металл.","Answer":"РУДА","Axis":"X"},{"Id":13,"X":5,"Y":9,"Clue":30,"Question":"Птица, благодаря которой появилось слово \"снайпер\".","Answer":"БЕКАС","Axis":"X"},{"Id":14,"X":0,"Y":10,"Clue":31,"Question":"Пернатый эталон величественной походки.","Answer":"ПАВА","Axis":"X"},{"Id":15,"X":11,"Y":10,"Clue":34,"Question":"Вертикальная или наклонная подземная горная выработка.","Answer":"ШУРФ","Axis":"X"},{"Id":16,"X":3,"Y":11,"Clue":36,"Question":"Действия Ермака по отношению к сибирским землям.","Answer":"ПОКОРЕНИЕ","Axis":"X"},{"Id":17,"X":0,"Y":13,"Clue":39,"Question":"Открытие сейфа с помощью автогена.","Answer":"ВЗЛОМ","Axis":"X"},{"Id":18,"X":10,"Y":13,"Clue":40,"Question":"Так называют жареное мясо на Востоке.","Answer":"КЕБАБ","Axis":"X"},{"Id":19,"X":5,"Y":14,"Clue":42,"Question":"Горделивый склад фигуры.","Answer":"СТАТЬ","Axis":"X"},{"Id":20,"X":0,"Y":15,"Clue":43,"Question":"Предохраняет местность от затопления водой.","Answer":"ДАМБА","Axis":"X"},{"Id":21,"X":10,"Y":15,"Clue":46,"Question":"\"… крепка и танки наши быстры\".","Answer":"БРОНЯ","Axis":"X"},{"Id":22,"X":4,"Y":16,"Clue":48,"Question":"Раскраска женских \"коготков\".","Answer":"МАНИКЮР","Axis":"X"},{"Id":23,"X":0,"Y":17,"Clue":50,"Question":"Одно из основных понятий математики.","Answer":"ЧИСЛО","Axis":"X"},{"Id":24,"X":10,"Y":17,"Clue":51,"Question":"Индейцы, очень часто встречающиеся в вестернах.","Answer":"АПАЧИ","Axis":"X"},{"Id":25,"X":4,"Y":18,"Clue":52,"Question":"Хитроумный кувырок циркового артиста.","Answer":"КУЛЬБИТ","Axis":"X"},{"Id":26,"X":0,"Y":0,"Clue":1,"Question":"Астрономическая дуга горизонта.","Answer":"АЗИМУТ","Axis":"Y"},{"Id":27,"X":2,"Y":0,"Clue":2,"Question":"Мясо, \"пережёванное\" мясорубкой.","Answer":"ФАРШ","Axis":"Y"},{"Id":28,"X":4,"Y":0,"Clue":3,"Question":"Особая примета Марьи-красы.","Answer":"КОСА","Axis":"Y"},{"Id":29,"X":7,"Y":0,"Clue":4,"Question":"Пренебрежительное название человека.","Answer":"ТИП","Axis":"Y"},{"Id":30,"X":10,"Y":0,"Clue":5,"Question":"Какой камень символизирует здоровье и долголетие?","Answer":"АГАТ","Axis":"Y"},{"Id":31,"X":12,"Y":0,"Clue":6,"Question":"Мадам Петухова как родня Ипполита Матвеевича.","Answer":"ТЁЩА","Axis":"Y"},{"Id":32,"X":14,"Y":0,"Clue":7,"Question":"Устаревшее название венгра.","Answer":"МАДЬЯР","Axis":"Y"},{"Id":33,"X":6,"Y":2,"Clue":11,"Question":"Ещё не реализовавшаяся опасность.","Answer":"УГРОЗА","Axis":"Y"},{"Id":34,"X":8,"Y":2,"Clue":12,"Question":"Что не ищут в стоге сена?","Answer":"ИГОЛКА","Axis":"Y"},{"Id":35,"X":3,"Y":3,"Clue":14,"Question":"Земляной вал под полотном дороги.","Answer":"НАСЫПЬ","Axis":"Y"},{"Id":36,"X":11,"Y":3,"Clue":16,"Question":"Одно из многочисленных колец на поверхности Луны.","Answer":"КРАТЕР","Axis":"Y"},{"Id":37,"X":1,"Y":5,"Clue":19,"Question":"Рок-группа с \"волей и разумом\".","Answer":"АРИЯ","Axis":"Y"},{"Id":38,"X":13,"Y":5,"Clue":21,"Question":"Музыкальное произведение виртуозного характера.","Answer":"ЭТЮД","Axis":"Y"},{"Id":39,"X":5,"Y":7,"Clue":23,"Question":"Полый стержень курительной трубки.","Answer":"ЧУБУК","Axis":"Y"},{"Id":40,"X":7,"Y":7,"Clue":24,"Question":"Глина, которую можно найти в пустыне.","Answer":"ТАКЫР","Axis":"Y"},{"Id":41,"X":9,"Y":7,"Clue":25,"Question":"Тащит с места работы всё, что плохо лежит.","Answer":"НЕСУН","Axis":"Y"},{"Id":42,"X":2,"Y":8,"Clue":27,"Question":"Нечто львиное в названии известного цветка.","Answer":"ЗЕВ","Axis":"Y"},{"Id":43,"X":12,"Y":8,"Clue":29,"Question":"Неразрывно связано с Шаолинем.","Answer":"УШУ","Axis":"Y"},{"Id":44,"X":1,"Y":10,"Clue":32,"Question":"Персидская серебряная монета, имевшая широкое распространение.","Answer":"АБАЗ","Axis":"Y"},{"Id":45,"X":3,"Y":10,"Clue":33,"Question":"Ничем не оправданная напыщенность и самоуверенность.","Answer":"АПЛОМБ","Axis":"Y"},{"Id":46,"X":11,"Y":10,"Clue":34,"Question":"Необыкновенно талантливое произведение искусства.","Answer":"ШЕДЕВР","Axis":"Y"},{"Id":47,"X":13,"Y":10,"Clue":35,"Question":"Таинственный древний символ скандинавского происхождения.","Answer":"РУНА","Axis":"Y"},{"Id":48,"X":6,"Y":11,"Clue":37,"Question":"Лицо \"владикавказской\" национальности.","Answer":"ОСЕТИН","Axis":"Y"},{"Id":49,"X":8,"Y":11,"Clue":38,"Question":"\"Уклонист\" в христианском вероучении.","Answer":"ЕРЕТИК","Axis":"Y"},{"Id":50,"X":0,"Y":13,"Clue":39,"Question":"По куску мыла каждому солдату.","Answer":"ВЫДАЧА","Axis":"Y"},{"Id":51,"X":14,"Y":13,"Clue":41,"Question":"\"Ты скажи, какая вина на мне, ...?\".","Answer":"БОЯРИН","Axis":"Y"},{"Id":52,"X":2,"Y":15,"Clue":44,"Question":"Продукт, который не приемлют вегетарианцы.","Answer":"МЯСО","Axis":"Y"},{"Id":53,"X":4,"Y":15,"Clue":45,"Question":"Внезапное психическое расстройство.","Answer":"АМОК","Axis":"Y"},{"Id":54,"X":10,"Y":15,"Clue":46,"Question":"Кинохит Алексея Балабанова с Сергеем Бодровым.","Answer":"БРАТ","Axis":"Y"},{"Id":55,"X":12,"Y":15,"Clue":47,"Question":"Единственный драгоценный камень, не имеющий кристаллической решётки.","Answer":"ОПАЛ","Axis":"Y"},{"Id":56,"X":7,"Y":16,"Clue":49,"Question":"Древнее государство и династия в Китае.","Answer":"ИНЬ","Axis":"Y"}]}